{

  "wall": {
    "height": {
      "label": "Height",
      "type": "number",
      "unit": "feet"
    },
    "length": {
      "label": "Length",
      "type": "number",
      "unit": "feet"
    },
    "unit": {
      "label": "Unit",
      "type": "select",
      "options": ["feet", "meters"]
    },
    "brickTypes": {
      "label": "Brick Type",
      "type": "select",
      "options": ["Clay Brick", "Cement Brick"]
    },
    "brickTypeOption": {
      "label": "Brick Type Options",
      "type": "radio",
      "options": [
        {"value": "singleBrick", "label": "Single Brick"},
        {"value": "doubleBrick", "label": "Double Brick"},
        {"value": "polishedBrick", "label": "Polished Brick"}
      ]
    }
  }

  ,
    "tiebeam": {
      "height": {
        "label": "Height",
        "type": "number",
        "unit": "feet"
      },
      "width": {
        "label": "Width",
        "type": "number",
        "unit": "feet"
      },
      "length": {
        "label": "Length",
        "type": "number",
        "unit": "feet"
      },
      "noOfTiebeams": {
        "label": "No of Tiebeams",
        "type": "number"
      },
      "unit": {
        "label": "Unit",
        "type": "select",
        "options": ["feet", "inches", "meters"]
      }
    },
    "stair": {
      "length": {
        "label": "Length",
        "type": "number",
        "unit": "feet"
      },
      "width": {
        "label": "Width",
        "type": "number",
        "unit": "feet"
      },
      "unit": {
        "label": "Unit",
        "type": "select",
        "options": ["feet", "inches", "meters"]
      },
      "noOfSteps": {
        "label": "No of Steps",
        "type": "number"
      },
      "thread": {
        "label": "Thread",
        "type": "number",
        "unit": "inches"
      },
      "riser": {
        "label": "Riser",
        "type": "number",
        "unit": "inches"
      },
      "thickness": {
        "label": "Thickness",
        "type": "number",
        "unit": "inches"
      }
    },
    "slab": {
      "thickness": {
        "label": "Thickness",
        "type": "number",
        "unit": "inches"
      },
      "width": {
        "label": "Width",
        "type": "number",
        "unit": "feet"
      },
      "length": {
        "label": "Length",
        "type": "number",
        "unit": "feet"
      },
      "unit": {
        "label": "Unit",
        "type": "select",
        "options": ["feet", "inches", "meters"]
      }
    },
    "column": {
      "height": {
        "label": "Height",
        "type": "number",
        "unit": "feet"
      },
      "width": {
        "label": "Width",
        "type": "number",
        "unit": "feet"
      },
      "length": {
        "label": "Length",
        "type": "number",
        "unit": "feet"
      },
      "unit": {
        "label": "Unit",
        "type": "select",
        "options": ["feet", "inches", "meters"]
      },
      "noOfColumns": {
        "label": "No of Columns",
        "type": "number"
      }
    },
    "window" :{
      "windowType": {
        "label": "Window Type",
        "type": "select",
        "options": ["Wooden", "Aluminium", "Steel"]
      },
      "quantity": {
        "label": "Quantity",
        "type": "number"
      },
      "price": {
        "label": "Price",
        "type": "number",
        "unit": "Rs"
      },
      "size":{
        "label": "Size",
        "type": "number"
      }
    },
    "door" :{
      "doorTypeId": {
        "label": "Door Type ID",
        "type": "select",
        "options": ["1", "2"]
      },
      "doorType": {
        "label": "Door Type",
        "type": "select",
        "options": ["Wooden Doors 7ft X 3ft", "Armee Teak Wooden Door 7ft X 3ft"]
      },
      "material": {
        "label": "Material",
        "type": "select",
        "options": ["tualang", "kempas", "teak"]
      },
      "quantity": {
        "label": "Quantity",
        "type": "number"
      }
    }
  }
  